revealpack/__init__.py
revealpack/__main__.py
revealpack/_utils/__init__.py
revealpack/_utils/config_operations.py
revealpack/_utils/file_operations.py
revealpack/_utils/html_operations.py
revealpack/_utils/presentation_operations.py
revealpack/_utils/string_operations.py
revealpack/_version.py
revealpack/assets/styles/revealpack.scss
revealpack/build.py
revealpack/cli.py
revealpack/package.py
revealpack/serve.py
revealpack/setup.py
revealpack-1.4.6.dist-info/METADATA
revealpack-1.4.6.dist-info/WHEEL
revealpack-1.4.6.dist-info/entry_points.txt
revealpack-1.4.6.dist-info/licenses/LICENSE
revealpack-1.4.6.dist-info/RECORD
