Metadata-Version: 2.4
Name: RevealPack
Version: 1.4.6
Summary: A CLI tool for managing Reveal.js presentation packages
License: MIT
License-File: LICENSE
Keywords: CLI,Reveal.js,presentation,slides,slide deck,presentation tools,HTML presentations,automation,package manager,documentation,theming,templating,Python,Markdown,web development,JavaScript,build system
Author: Khris Griffis, Ph.D.
Author-email: khris.griffis.phd@gmail.com
Requires-Python: >=3.12,<4.0
Classifier: License :: OSI Approved :: MIT License
Classifier: Operating System :: OS Independent
Classifier: Programming Language :: Python :: 3
Classifier: Programming Language :: Python :: 3.12
Classifier: Programming Language :: Python :: 3.13
Classifier: Programming Language :: Python :: 3.14
Requires-Dist: beautifulsoup4
Requires-Dist: click
Requires-Dist: jinja2
Requires-Dist: pyyaml
Requires-Dist: requests
Requires-Dist: watchdog
Project-URL: Documentation, https://revealpack.readthedocs.io/en/latest/
Project-URL: Homepage, https://github.com/Khlick/RevealPack
Project-URL: Issues, https://github.com/Khlick/RevealPack/issues
Project-URL: Repository, https://github.com/Khlick/RevealPack
